base_class_autotests/__init__.py
base_class_autotests/base_class_autotests.py
base_class_autotests-2.0.0.dist-info/LICENSE
base_class_autotests-2.0.0.dist-info/METADATA
base_class_autotests-2.0.0.dist-info/WHEEL
base_class_autotests-2.0.0.dist-info/top_level.txt
base_class_autotests-2.0.0.dist-info/RECORD
