Metadata-Version: 2.1
Name: base-class-autotests
Version: 2.0.0
Summary: Base class with basic checks of the elements
Home-page: https://coderepo.corp.tander.ru/mishin_va/basic_checks
Author: Kostuchenko_VA, Mishin_VA
Author-email: kostuchenko_va@magnit.ru, mishin_va@magnit.ru
Classifier: Programming Language :: Python :: 3.9
Classifier: License :: OSI Approved :: GNU General Public License v3 (GPLv3)
License-File: LICENSE
Requires-Dist: selenium (==4.9.0)
Requires-Dist: allure-pytest (==2.13.1)
